{
  "mouthCues": [
    {
      "start": 0,
      "end": 50,
      "value": 0
    },
    {
      "start": 50,
      "end": 100,
      "value": 12
    },
    {
      "start": 100,
      "end": 225,
      "value": 9
    },
    {
      "start": 225,
      "end": 300,
      "value": 19
    },
    {
      "start": 300,
      "end": 337.5,
      "value": 7
    },
    {
      "start": 337.5,
      "end": 375,
      "value": 6
    },
    {
      "start": 375,
      "end": 400,
      "value": 7
    },
    {
      "start": 400,
      "end": 475,
      "value": 13
    },
    {
      "start": 475,
      "end": 525,
      "value": 6
    },
    {
      "start": 525,
      "end": 562.5,
      "value": 19
    },
    {
      "start": 562.5,
      "end": 687.5,
      "value": 13
    },
    {
      "start": 687.5,
      "end": 775,
      "value": 6
    },
    {
      "start": 775,
      "end": 900,
      "value": 18
    },
    {
      "start": 900,
      "end": 962.5,
      "value": 17
    },
    {
      "start": 962.5,
      "end": 987.5,
      "value": 1
    },
    {
      "start": 987.5,
      "end": 1050,
      "value": 15
    },
    {
      "start": 1050,
      "end": 1187.5,
      "value": 4
    },
    {
      "start": 1187.5,
      "end": 1262.5,
      "value": 20
    },
    {
      "start": 1262.5,
      "end": 1325,
      "value": 1
    },
    {
      "start": 1325,
      "end": 1375,
      "value": 19
    },
    {
      "start": 1375,
      "end": 1400,
      "value": 19
    },
    {
      "start": 1400,
      "end": 1425,
      "value": 12
    },
    {
      "start": 1425,
      "end": 1587.5,
      "value": 11
    },
    {
      "start": 1587.5,
      "end": 1712.5,
      "value": 1
    },
    {
      "start": 1712.5,
      "end": 1800,
      "value": 15
    },
    {
      "start": 1800,
      "end": 1825,
      "value": 19
    },
    {
      "start": 1825,
      "end": 1850,
      "value": 15
    },
    {
      "start": 1850,
      "end": 1900,
      "value": 1
    },
    {
      "start": 1900,
      "end": 2025,
      "value": 14
    },
    {
      "start": 2025,
      "end": 2075,
      "value": 1
    },
    {
      "start": 2075,
      "end": 2125,
      "value": 13
    },
    {
      "start": 2125,
      "end": 2175,
      "value": 6
    },
    {
      "start": 2175,
      "end": 2275,
      "value": 18
    },
    {
      "start": 2275,
      "end": 2350,
      "value": 13
    },
    {
      "start": 2350,
      "end": 2400,
      "value": 2
    },
    {
      "start": 2400,
      "end": 2425,
      "value": 21
    },
    {
      "start": 2425,
      "end": 2512.5,
      "value": 1
    },
    {
      "start": 2512.5,
      "end": 2537.5,
      "value": 19
    },
    {
      "start": 2537.5,
      "end": 2575,
      "value": 6
    },
    {
      "start": 2575,
      "end": 2612.5,
      "value": 21
    },
    {
      "start": 2612.5,
      "end": 2662.5,
      "value": 21
    },
    {
      "start": 2662.5,
      "end": 2762.5,
      "value": 14
    },
    {
      "start": 2762.5,
      "end": 2837.5,
      "value": 10
    },
    {
      "start": 2837.5,
      "end": 2962.5,
      "value": 6
    },
    {
      "start": 2962.5,
      "end": 3062.5,
      "value": 19
    },
    {
      "start": 3062.5,
      "end": 3175,
      "value": 4
    },
    {
      "start": 3175,
      "end": 3212.5,
      "value": 6
    },
    {
      "start": 3212.5,
      "end": 3250,
      "value": 21
    },
    {
      "start": 3250,
      "end": 3300,
      "value": 1
    },
    {
      "start": 3300,
      "end": 3350,
      "value": 14
    },
    {
      "start": 3350,
      "end": 3550,
      "value": 0
    }
  ]
}